ffmpeg_update/__init__.py
ffmpeg_update/__main__.py
ffmpeg_update/py.typed
ffmpeg_update-3.0.1.dist-info/WHEEL
ffmpeg_update-3.0.1.dist-info/entry_points.txt
ffmpeg_update-3.0.1.dist-info/METADATA
ffmpeg_update-3.0.1.dist-info/RECORD
