Metadata-Version: 2.3
Name: ffmpeg-update
Version: 3.0.1
Summary: Package manager for FFmpeg, FFprobe, and FFplay static binaries
Keywords: updater,installer,downloader,program,executable,binary,command,line,cli,tool
Author: Asadullah Shaikh
Classifier: Development Status :: 5 - Production/Stable
Classifier: Environment :: Console
Classifier: Intended Audience :: Developers
Classifier: Intended Audience :: End Users/Desktop
Classifier: Intended Audience :: System Administrators
Classifier: Operating System :: MacOS
Classifier: Operating System :: POSIX :: Linux
Classifier: Programming Language :: Python :: 3
Classifier: Topic :: Multimedia
Classifier: Topic :: Software Development :: Libraries :: Python Modules
Classifier: Topic :: System :: Installation/Setup
Classifier: Topic :: System :: Software Distribution
Classifier: Topic :: Terminals
Classifier: Topic :: Utilities
Classifier: Typing :: Typed
Requires-Dist: cyclopts>=4.0.0,<5.0.0
Requires-Dist: niquests>=3.15.2,<4.0.0
Requires-Dist: rich>=14.2.0,<15.0.0
Requires-Python: >=3.10
Project-URL: Repository, https://github.com/pantheraleo-7/ffmpeg-update
